pydta/__init__.py
pydta/data/dta_sample_data/dta_sample_data.json
pydta/data/dta_sample_data/dta_sample_data_mini.json
pydta/data/representation/dont_delete.txt
pydta/data/vocabs/chemical/chembl27_enc_94.json
pydta/data/vocabs/chemical/chembl27_enc_bpe_8000.json
pydta/data/vocabs/chemical/chembl27_encoding.json
pydta/data/vocabs/protein/uniprot_26.json
pydta/data/vocabs/protein/uniprot_bpe_32000.json
pydta/evaluation/__init__.py
pydta/evaluation/evaluation.py
pydta/models/__init__.py
pydta/models/bowdta.py
pydta/models/bpedta.py
pydta/models/chemboost.py
pydta/models/debiaseddta.py
pydta/models/deepdta.py
pydta/models/dta_model.py
pydta/models/iddta.py
pydta/models/lmdta.py
pydta/utils/__init__.py
pydta/utils/utils.py
pydta-0.0.3.dist-info/LICENSE
pydta-0.0.3.dist-info/METADATA
pydta-0.0.3.dist-info/WHEEL
pydta-0.0.3.dist-info/top_level.txt
pydta-0.0.3.dist-info/RECORD
